<?xml version="1.0" encoding="UTF-8"?>
<!DOCTYPE ui:UiBinder SYSTEM "http://dl.google.com/gwt/DTD/xhtml.ent">
<ui:UiBinder xmlns:ui="urn:ui:com.google.gwt.uibinder" xmlns:g="urn:import:com.google.gwt.user.client.ui"
    xmlns:d="urn:import:org.ovirt.engine.ui.common.widget.dialog" xmlns:e="urn:import:org.ovirt.engine.ui.common.widget.editor"
    xmlns:w="urn:import:org.ovirt.engine.ui.common.widget" xmlns:ge="urn:import:org.ovirt.engine.ui.common.widget.editor.generic"
    xmlns:b="urn:import:org.gwtbootstrap3.client.ui">

    <ui:with field='resources' type='org.ovirt.engine.ui.userportal.ApplicationResources' />
    <ui:with field='constants' type='org.ovirt.engine.ui.userportal.ApplicationConstants'/>

    <ui:style>
        .loginForm:focus {
            outline: 0;
        }

        .container {
            padding-top: 10px !important;
        }

        .label-default {
            background-color: inherit;
        }

        .login-link:hover, login-link:focus {
            color: #00618a;
            text-decoration: underline;
        }

        .login-link {
            color: #0099d3;
        }

        .login-error {
            color: #b94a48;
            background-color: inherit;
            border-color: #b94a48;
        }

        .login-message-error {
            color: #b94a48;
            background-color: inherit;
            word-break: break-word;
            white-space: normal;
        }

        .information-triangle {
            font-size: 20px;
        }

        .information-message {
            font-size: 13px;
            font-weight: 600;
            white-space: normal;
        }

        .motd-header {
            font-size: 14px;
            font-weight: 600;
            padding-top: 20px;
            padding-bottom: 5px;
        }

        .loginButtonContainer {
            padding-right: 0 !important;
        }

        @external obrand_loginFormLogoImage;
            .obrand_loginFormLogoImage {
        }
    </ui:style>

    <g:FocusPanel ui:field="loginForm">
    <g:HTMLPanel>
    <div class="modal-dialog">
        <div class="modal-content modal-login-container">
            <div class="modal-header">
                <g:HTMLPanel ui:field="informationMessagePanel" />
                <g:HTMLPanel ui:field="motdPanel" addStyleNames="{style.label-default}">
-                	<b:Label ui:field="motdHeaderLabel" styleName="{style.motd-header}" />
-                	<g:HTMLPanel ui:field="motdMessagePanel" addStyleNames="temp-link-color" />
-            	</g:HTMLPanel>
            </div>
            <div class="modal-body">
                <b:Alert ui:field="errorMessagePanel" addStyleNames="alert-danger">
                    <b:Label styleName="" ui:field="errorMessage"/>
                </b:Alert>
                <div class="modal-form-container">
                    <div class="row" style="margin-bottom: 10px;">
                        <div class="col-xs-6">
                            <b:Label styleName="" text="{constants.loginButtonLabel}"/>
                        </div>
                        <div class="col-xs-6">
                            <div class="btn-group pull-right">
                                <b:ListBox ui:field="localeBox" />
                            </div>
                        </div>
                    </div>
                    <form role="form">
                        <div class="form-group">
                            <div class="inner-addon left-addon">
                                <i class="fa fa-user"></i>
                                <b:Input styleName="form-control" type="TEXT" placeholder="{constants.loginFormUserNameLabel}" ui:field="userNameEditor"></b:Input>
                            </div>
                        </div>

                        <div class="form-group">
                            <div class="inner-addon left-addon">
                                <i class="fa fa-key"></i>
                                <b:Input styleName="form-control" type="PASSWORD" placeholder="{constants.loginFormPasswordLabel}" ui:field="passwordEditor"></b:Input>
                            </div>
                        </div>

                        <div class="form-group">
                            <div class="inner-addon left-addon">
                                <i class="fa fa-puzzle-piece" />
                                <b:ListBox ui:field="profileEditor" />
                            </div>
                        </div>

                        <div>
                            <ge:EntityModelCheckBoxEditor ui:field="connectAutomaticallyEditor" usePatternFly="true" />
                        </div>

                        <w:PatternflyUiCommandButton styleName="btn btn-primary btn-block" ui:field="loginButton"></w:PatternflyUiCommandButton>
                    </form>
                </div>
            </div>
        </div>
    </div>
    </g:HTMLPanel>
    </g:FocusPanel>

</ui:UiBinder>
